unicode2hex/__init__.py
unicode2hex/main.py
unicode2hex-0.0.1.dist-info/entry_points.txt
unicode2hex-0.0.1.dist-info/WHEEL
unicode2hex-0.0.1.dist-info/METADATA
unicode2hex-0.0.1.dist-info/RECORD
