Metadata-Version: 2.1
Name: unicode2hex
Version: 0.0.1
Summary: Help get utf-8 hex representation of a unicode value or character
Home-page: https://github.com/tizee/unicode2hex
Keywords: script,unicode,utf-8
Author: tizee
Requires-Python: >=3.7,<4.0
Classifier: Development Status :: 4 - Beta
Classifier: Programming Language :: Python :: 3
Classifier: Programming Language :: Python :: 3.7
Classifier: Programming Language :: Python :: 3.8
Classifier: Programming Language :: Python :: 3.9
Project-URL: Repository, https://github.com/tizee/unicode2hex
